linien_common/__init__.py
linien_common/common.py
linien_common/communication.py
linien_common/config.py
linien_common/influxdb.py
linien_common-2.1.0.dist-info/METADATA
linien_common-2.1.0.dist-info/WHEEL
linien_common-2.1.0.dist-info/top_level.txt
linien_common-2.1.0.dist-info/RECORD
