Metadata-Version: 2.1
Name: linien-common
Version: 2.1.0
Summary: Shared components of the Linien spectroscopy lock application.
Author-email: Benjamin Wiegand <benjamin.wiegand@physik.hu-berlin.de>, Bastian Leykauf <leykauf@physik.hu-berlin.de>, Robert Jördens <rj@quartiq.de>, Christian Freier <christian.freier@gmail.com>, Doron Behar <doron.behar@gmail.com>
Maintainer-email: Bastian Leykauf <leykauf@physik.hu-berlin.de>
Project-URL: Homepage, https://github.com/linien-org/linien
Classifier: Programming Language :: Python :: 3
Classifier: License :: OSI Approved :: GNU General Public License v3 (GPLv3)
Classifier: Operating System :: OS Independent
Requires-Python: >=3.8
Requires-Dist: appdirs <2.0,>=1.4.4
Requires-Dist: importlib-metadata <9.0,>=2.1.3
Requires-Dist: numpy <2.0,>=1.21.5
Requires-Dist: rpyc <7.0,>=6.0
Requires-Dist: scipy <2.0,>=1.8.0
Provides-Extra: dev
Requires-Dist: black >=22.8.0 ; extra == 'dev'
Requires-Dist: pre-commit >=2.20.0 ; extra == 'dev'
Requires-Dist: flake8 >=5.0.4 ; extra == 'dev'
Requires-Dist: isort >=5.10.1 ; extra == 'dev'
Requires-Dist: flake8-pyproject >=1.2.3 ; extra == 'dev'
Requires-Dist: setuptools-scm >=6.2 ; extra == 'dev'
